helloworldpy/__init__.py
helloworldpy/__main__.py
helloworldpy-1.1.1.dist-info/LICENSE
helloworldpy-1.1.1.dist-info/METADATA
helloworldpy-1.1.1.dist-info/WHEEL
helloworldpy-1.1.1.dist-info/entry_points.txt
helloworldpy-1.1.1.dist-info/top_level.txt
helloworldpy-1.1.1.dist-info/RECORD
