Metadata-Version: 2.1
Name: helloworldpy
Version: 1.1.1
Summary: This a basic project for learning how to make PIP(PyPI) package
Home-page: https://github.com/Saketh-Chandra/helloworldpy
Author: Saketh Chandra
Author-email: b.sakethchandra9@gmail.com
License: MIT
Keywords: Hello,World,Hello-World,Hello python,Bulls and Cows,checkip
Platform: UNKNOWN
Classifier: Development Status :: 5 - Production/Stable
Classifier: Environment :: Console
Classifier: Intended Audience :: Education
Classifier: Operating System :: MacOS :: MacOS X
Classifier: Operating System :: Microsoft :: Windows
Classifier: Operating System :: POSIX
Classifier: Programming Language :: Python
Classifier: License :: OSI Approved :: MIT License
Classifier: Programming Language :: Python :: 3.6
Classifier: Programming Language :: Python :: 3.7
Classifier: Programming Language :: Python :: 3.8
Classifier: Programming Language :: Python :: 3.9
Requires-Dist: requests
Requires-Dist: idna (>=2.7)
